odoo10_addon_hr_timesheet_sheet_period-10.0.1.0.0.99.dev5-py2.7-nspkg.pth
odoo/addons/hr_timesheet_sheet_period/README.rst
odoo/addons/hr_timesheet_sheet_period/__init__.py
odoo/addons/hr_timesheet_sheet_period/__manifest__.py
odoo/addons/hr_timesheet_sheet_period/i18n/hr_timesheet_sheet_period.pot
odoo/addons/hr_timesheet_sheet_period/i18n/it.po
odoo/addons/hr_timesheet_sheet_period/models/__init__.py
odoo/addons/hr_timesheet_sheet_period/models/hr_timesheet_sheet.py
odoo/addons/hr_timesheet_sheet_period/static/description/icon.png
odoo/addons/hr_timesheet_sheet_period/tests/__init__.py
odoo/addons/hr_timesheet_sheet_period/tests/test_hr_timesheet_sheet_period.py
odoo/addons/hr_timesheet_sheet_period/views/hr_timesheet_sheet_view.xml
odoo10_addon_hr_timesheet_sheet_period-10.0.1.0.0.99.dev5.dist-info/METADATA
odoo10_addon_hr_timesheet_sheet_period-10.0.1.0.0.99.dev5.dist-info/RECORD
odoo10_addon_hr_timesheet_sheet_period-10.0.1.0.0.99.dev5.dist-info/WHEEL
odoo10_addon_hr_timesheet_sheet_period-10.0.1.0.0.99.dev5.dist-info/namespace_packages.txt
odoo10_addon_hr_timesheet_sheet_period-10.0.1.0.0.99.dev5.dist-info/top_level.txt
